buf/__init__.py
buf/validate/__init__.py
buf/validate/expression_pb2.py
buf/validate/expression_pb2_grpc.py
buf/validate/priv/private_pb2.py
buf/validate/priv/private_pb2_grpc.py
buf/validate/validate_pb2.py
buf/validate/validate_pb2_grpc.py
google/api/annotations_pb2.py
google/api/annotations_pb2_grpc.py
google/api/http_pb2.py
google/api/http_pb2_grpc.py
google/protobuf/descriptor_pb2.py
google/protobuf/descriptor_pb2_grpc.py
google/protobuf/duration_pb2.py
google/protobuf/duration_pb2_grpc.py
google/protobuf/timestamp_pb2.py
google/protobuf/timestamp_pb2_grpc.py
groq/__init__.py
groq/cloud/__init__.py
groq/cloud/core/__init__.py
groq/cloud/core/auth.py
groq/cloud/core/core.py
groq/cloud/core/exceptions.py
groq/cloud/core/types.py
groq/cloud/openai/__init__.py
groq/cloud/openai/openai.py
public/llmcloud/globalstatsmanager/v1/globalstatsmanager_pb2.py
public/llmcloud/globalstatsmanager/v1/globalstatsmanager_pb2_grpc.py
public/llmcloud/modelmanager/v1/model_pb2.py
public/llmcloud/modelmanager/v1/model_pb2_grpc.py
public/llmcloud/modelmanager/v1/modelmanager_pb2.py
public/llmcloud/modelmanager/v1/modelmanager_pb2_grpc.py
public/llmcloud/queuestatemanager/v1/queuestatemanager_pb2.py
public/llmcloud/queuestatemanager/v1/queuestatemanager_pb2_grpc.py
public/llmcloud/requestmanager/v1/requestmanager_pb2.py
public/llmcloud/requestmanager/v1/requestmanager_pb2_grpc.py
groq-0.2.0.dist-info/METADATA
groq-0.2.0.dist-info/WHEEL
groq-0.2.0.dist-info/RECORD
