Metadata-Version: 2.1
Name: groq
Version: 0.2.0
Summary: The GroqAPI Python SDK
Author: Rohit Khaire
Author-email: rkhaire@groq.com
Requires-Python: >=3.10,<4.0
Classifier: Programming Language :: Python :: 3
Classifier: Programming Language :: Python :: 3.10
Classifier: Programming Language :: Python :: 3.11
Classifier: Programming Language :: Python :: 3.12
Requires-Dist: google-api-python-client (>=2.111.0,<3.0.0)
Requires-Dist: google-cloud (>=0.34.0,<0.35.0)
Requires-Dist: grpc-stubs (>=1.53.0.5,<2.0.0.0)
Requires-Dist: grpcio (>=1.60.0,<2.0.0)
Requires-Dist: protobuf (==3.20.3)
Requires-Dist: types-protobuf (>=4.24.0.4,<5.0.0.0)
Requires-Dist: types-requests (>=2.31.0.20231231,<3.0.0.0)
